{"type":"object","description":"AWS-specific platform permission configuration","required":["grant","binding"],"properties":{"binding":{"description":"How to bind the permissions (stack vs resource scope)","type":"object","properties":{"resource":{"type":"object","description":"AWS-specific binding specification","required":["resources"],"properties":{"condition":{"type":["object","null"],"description":"Optional condition for additional filtering (rare)","additionalProperties":{"type":"object","additionalProperties":{"type":"string"},"propertyNames":{"type":"string"}},"propertyNames":{"type":"string"}},"resources":{"type":"array","items":{"type":"string"},"description":"Resource ARNs to bind to"}},"additionalProperties":false},"stack":{"type":"object","description":"AWS-specific binding specification","required":["resources"],"properties":{"condition":{"type":["object","null"],"description":"Optional condition for additional filtering (rare)","additionalProperties":{"type":"object","additionalProperties":{"type":"string"},"propertyNames":{"type":"string"}},"propertyNames":{"type":"string"}},"resources":{"type":"array","items":{"type":"string"},"description":"Resource ARNs to bind to"}},"additionalProperties":false}},"additionalProperties":false,"x-readme-ref-name":"BindingConfiguration_AwsBindingSpec"},"grant":{"description":"What permissions to grant","type":"object","properties":{"actions":{"type":["array","null"],"items":{"type":"string"},"description":"AWS IAM actions (only for AWS)"},"dataActions":{"type":["array","null"],"items":{"type":"string"},"description":"Azure actions (only for Azure)"},"permissions":{"type":["array","null"],"items":{"type":"string"},"description":"GCP permissions (only for GCP)"}},"additionalProperties":false,"x-readme-ref-name":"PermissionGrant"}},"additionalProperties":false,"x-readme-ref-name":"AwsPlatformPermission"}