{"type":"object","description":"Autoscaling configuration for stateless containers.","required":["min","desired","max"],"properties":{"desired":{"type":"integer","format":"int32","description":"Initial desired replicas at container creation","minimum":0},"max":{"type":"integer","format":"int32","description":"Maximum replicas under load","minimum":0},"maxHttpP95LatencyMs":{"type":["number","null"],"format":"double","description":"Maximum acceptable p95 HTTP latency in milliseconds"},"min":{"type":"integer","format":"int32","description":"Minimum replicas (always running)","minimum":0},"targetCpuPercent":{"type":["number","null"],"format":"double","description":"Target CPU utilization percentage for scaling (default: 70%)"},"targetHttpInFlightPerReplica":{"type":["integer","null"],"format":"int32","description":"Target in-flight HTTP requests per replica","minimum":0},"targetMemoryPercent":{"type":["number","null"],"format":"double","description":"Target memory utilization percentage for scaling (default: 80%)"}},"x-readme-ref-name":"ContainerAutoscaling"}