{"type":"object","description":"GCP Build ImportData — Cloud Build trigger + worker pool reference.","required":["projectId","region","triggerId","triggerName","buildEnvVars","serviceAccountEmail"],"properties":{"buildEnvVars":{"type":"object","description":"Environment variables stamped into the trigger's substitutions.","additionalProperties":{"type":"string"},"propertyNames":{"type":"string"}},"projectId":{"type":"string","description":"Project ID hosting the trigger."},"region":{"type":"string","description":"Region where the trigger runs."},"serviceAccountEmail":{"type":"string","description":"Service account email Cloud Build uses when running builds."},"triggerId":{"type":"string","description":"Cloud Build trigger ID."},"triggerName":{"type":"string","description":"Cloud Build trigger name."}},"x-readme-ref-name":"GcpBuildImportData"}