{
  "type": "object",
  "required": ["reason", "message"],
  "properties": {
    "count": { "type": ["integer", "null"], "format": "int32" },
    "eventTime": { "type": ["string", "null"], "format": "date-time" },
    "firstTimestamp": { "type": ["string", "null"], "format": "date-time" },
    "involvedObject": {
      "oneOf": [
        { "type": "null" },
        {
          "type": "object",
          "properties": {
            "apiVersion": { "type": ["string", "null"] },
            "fieldPath": { "type": ["string", "null"] },
            "kind": { "type": ["string", "null"] },
            "name": { "type": ["string", "null"] },
            "namespace": { "type": ["string", "null"] },
            "resourceVersion": { "type": ["string", "null"] },
            "uid": { "type": ["string", "null"] }
          },
          "x-readme-ref-name": "KubernetesEventInvolvedObject"
        }
      ]
    },
    "lastTimestamp": { "type": ["string", "null"], "format": "date-time" },
    "message": { "type": "string" },
    "raw": { "oneOf": [{ "type": "null" }, { "x-readme-ref-name": "Value" }] },
    "reason": { "type": "string" },
    "source": {
      "oneOf": [
        { "type": "null" },
        {
          "type": "object",
          "properties": {
            "component": { "type": ["string", "null"] },
            "host": { "type": ["string", "null"] }
          },
          "x-readme-ref-name": "KubernetesEventSource"
        }
      ]
    },
    "type": { "type": ["string", "null"] }
  },
  "x-readme-ref-name": "KubernetesEventSnapshot"
}
